{
    "Schema1": null,
    "Schema2": null,
    "Schema3": [
        {
            "Date": "2021-02-20T15:42:57.0Z",
            "DoneBy": "Dr Gemma Deakin (GP Surgery) ",
            "Location": "HSCIC GP Demo 9 (General Practice)",
            "RecordItems": [
                {
                    "Type": "Vaccination",
                    "Details": "COVID-19 mRNA Vac BNT162b2 30mcg/0.3ml conc for susp for inj multidose vials (Pfizer-BioNTech) 2 0.3ml",
                    "BinaryDataId": null,
                    "Url": null
                }
            ]
        },
        {
            "Date": "2021-03-20T16:40:57.0Z",
            "DoneBy": "Dr Gemma Deakin (GP Surgery) ",
            "Location": "HSCIC GP Demo 9 (General Practice)",
            "RecordItems": [
                {
                    "Type": "Vaccination",
                    "Details": "COVID-19 mRNA Vac BNT162b2 30mcg/0.3ml conc for susp for inj multidose vials (Pfizer-BioNTech) 1 0.3ml",
                    "BinaryDataId": null,
                    "Url": null
                }
            ]
        }
    ],
    "RequestId": "f32141f9-5fcc-49de-84d5-89dfb54977ae",
    "patientId": "bbb1b99c-0ad9-4582-bae5-79abfa295acf",
    "PatientDetails": {
        "surname": "Laurence",
        "dateOfBirth": "1917-07-06",
        "linkageKey": "h%Y5\\GgMX9ev8dq7",
        "accountID": "799531240",
        "gpOdsCode": "9HSCIC"
    }
}